ekansnake_cli_game-1.0.3.dist-info/licenses/LICENSE
ekansnake_game/__init__.py
ekansnake_game/__main__.py
ekansnake_cli_game-1.0.3.dist-info/METADATA
ekansnake_cli_game-1.0.3.dist-info/WHEEL
ekansnake_cli_game-1.0.3.dist-info/entry_points.txt
ekansnake_cli_game-1.0.3.dist-info/top_level.txt
ekansnake_cli_game-1.0.3.dist-info/RECORD
