Metadata-Version: 2.4
Name: ekansnake-cli-game
Version: 1.0.3
Summary: A CLI Snake Game with obstacles and high scores
Home-page: https://github.com/AbhishekJha3511/cli-snake-game
Author: Abhishek Jha
Classifier: Programming Language :: Python :: 3
Classifier: License :: OSI Approved :: MIT License
Classifier: Operating System :: OS Independent
Requires-Python: >=3.6
License-File: LICENSE
Requires-Dist: windows-curses; platform_system == "Windows"
Dynamic: author
Dynamic: classifier
Dynamic: description-content-type
Dynamic: home-page
Dynamic: license-file
Dynamic: requires-dist
Dynamic: requires-python
Dynamic: summary
